zuid/__init__.py
zuid/zuid.py
zuid-0.1.1.dist-info/LICENSE
zuid-0.1.1.dist-info/WHEEL
zuid-0.1.1.dist-info/METADATA
zuid-0.1.1.dist-info/RECORD
