Metadata-Version: 2.1
Name: zuid
Version: 0.1.1
Summary: Random prefixed ids
License: MIT
Author: Pedro Werneck
Author-email: pjwerneck@gmail.com
Requires-Python: >=3.5,<4.0
Classifier: License :: OSI Approved :: MIT License
Classifier: Programming Language :: Python :: 3
Classifier: Programming Language :: Python :: 3.5
Classifier: Programming Language :: Python :: 3.6
Classifier: Programming Language :: Python :: 3.7
